tests/__init__.py
catboost_no_sse4-1.2.5.2.dist-info/top_level.txt
catboost_no_sse4-1.2.5.2.dist-info/RECORD
catboost_no_sse4-1.2.5.2.dist-info/METADATA
catboost_no_sse4-1.2.5.2.dist-info/WHEEL
catboost/version.py
catboost/metrics.py
catboost/carry.py
catboost/dev_utils.py
catboost/utils.py
catboost/monoforest.py
catboost/core.py
catboost/datasets.py
catboost/_catboost.so
catboost/plot_helpers.py
catboost/__init__.py
catboost/text_processing.py
catboost/widget/ipythonwidget.py
catboost/widget/catboost-widget.json
catboost/widget/callbacks.py
catboost/widget/metrics_plotter.py
catboost/widget/__init__.py
catboost/widget/js/.eslintrc
catboost/widget/js/yarn.lock
catboost/widget/js/package.json
catboost/widget/js/webpack.config.js
catboost/widget/js/src/index.js
catboost/widget/js/src/CatboostIpython.js
catboost/widget/js/src/CatboostIpython.css
catboost/widget/js/src/embed.js
catboost/widget/js/src/extension.js
catboost/widget/js/src/labplugin.js
catboost/eval/log_config.py
catboost/eval/_fold_storage.py
catboost/eval/factor_utils.py
catboost/eval/_fold_models_handler.py
catboost/eval/catboost_evaluation.py
catboost/eval/_readers.py
catboost/eval/_splitter.py
catboost/eval/utils.py
catboost/eval/execution_case.py
catboost/eval/__init__.py
catboost/eval/evaluation_result.py
catboost/eval/_fold_model.py
